proglog/__init__.py
proglog/proglog.py
proglog/version.py
proglog-0.1.10.dist-info/LICENSE
proglog-0.1.10.dist-info/METADATA
proglog-0.1.10.dist-info/WHEEL
proglog-0.1.10.dist-info/top_level.txt
proglog-0.1.10.dist-info/RECORD
