Metadata-Version: 2.1
Name: proglog
Version: 0.1.10
Summary: Log and progress bar manager for console, notebooks, web...
Author: Zulko
License: MIT
Keywords: logger log progress bar
Platform: UNKNOWN
License-File: LICENSE
